Workbook

Sheet Cover
A1: RKLB 3-Statement + DCF Model
A4: Company | B4: Rocket Lab Corp
A5: Ticker | B5: RKLB
A6: Model output | B6: C:\Users\M\Desktop\buy-side-research-skills-1.1.0\examples\financial-data-pull\us\rklb\rklb-3statement-dcf-model.xlsx
A7: Source pack | B7: C:\Users\M\Desktop\buy-side-research-skills-1.1.0\examples\financial-data-pull\us\rklb
A8: Primary filing | B8: FY2025 10-K, filed 2026-02-26, accession 0001819994-26-000013
A9: Historical actuals | B9: FY2023-FY2025 from financial-data / SEC XBRL
A10: Forecast horizon | B10: FY2026E-FY2030E
A11: Revenue build | B11: Launch Services + Space Systems Products + Space Systems Services
A12: Key modeling caveat | B12: Backlog is disclosed only at company level; do not allocate by segment without new source.

Sheet Sources
A1: Sources and Model Caveats
A4: financial-data-summary.md | B4: Public financial-data summary for human/LLM review.
A5: internal/financial-data/actuals-resolved.json | B5: Machine historical actuals; missing/unmapped policy says leave blank and flag review.
A6: internal/financial-data/evidence-pack.json | B6: Completeness, source-map, cross-check and latest run pointer.
A7: internal/financial-data/full-filing.md | B7: Internal FY2025 10-K text retained for audit/deeper lookup.
A8: driver-map.md | B8: Public driver-map summary for revenue split and modeling treatment.
A9: internal/driver-map/driver-map.json | B9: Machine driver-map input for revenue build assumptions.
A12: Critical Caveats
A13: Caveat 1 | B13: Launch cadence and ASP are not in the financial-data pack; they need a sourced launch manifest before being model-ready.
A14: Caveat 2 | B14: Neutron is modeled as scenario optionality, not historical run-rate.
A15: Caveat 3 | B15: Company backlog was $1.847bn at FY2025, but no segment split is disclosed.
A16: Caveat 4 | B16: Forecast assumptions are illustrative and editable blue inputs, not management guidance.

Sheet Assumptions
A1: Forecast and Valuation Assumptions
A3: $ in millions, except per-share data | B3: FY2023A | C3: FY2024A | D3: FY2025A | E3: FY2026E | F3: FY2027E | G3: FY2028E | H3: FY2029E | I3: FY2030E
A5: Operating Assumptions
A6: Launch revenue growth | E6: 0.3 | F6: 0.25 | G6: 0.22 | H6: 0.18 | I6: 0.15
A7: Space Systems products growth | E7: 0.25 | F7: 0.22 | G7: 0.2 | H7: 0.18 | I7: 0.16
A8: Space Systems services growth | E8: 0.28 | F8: 0.25 | G8: 0.22 | H8: 0.2 | I8: 0.18
A9: Launch gross margin | E9: 0.42 | F9: 0.43 | G9: 0.44 | H9: 0.45 | I9: 0.46
A10: Space Systems products gross margin | E10: 0.32 | F10: 0.33 | G10: 0.34 | H10: 0.35 | I10: 0.36
A11: Space Systems services gross margin | E11: 0.23 | F11: 0.24 | G11: 0.25 | H11: 0.26 | I11: 0.27
A12: R&D % revenue | E12: 0.42 | F12: 0.38 | G12: 0.34 | H12: 0.3 | I12: 0.27
A13: SG&A % revenue | E13: 0.24 | F13: 0.22 | G13: 0.2 | H13: 0.18 | I13: 0.16
A14: D&A % revenue | E14: 0.07 | F14: 0.065 | G14: 0.06 | H14: 0.055 | I14: 0.05
A15: SBC % revenue | E15: 0.1 | F15: 0.09 | G15: 0.08 | H15: 0.07 | I15: 0.06
A16: CapEx % revenue | E16: 0.16 | F16: 0.14 | G16: 0.12 | H16: 0.1 | I16: 0.08
A17: AR % revenue | E17: 0.065 | F17: 0.064 | G17: 0.063 | H17: 0.062 | I17: 0.061
... A25: Share dilution | E25: 0.03 | F25: 0.03 | G25: 0.03 | H25: 0.03 | I25: 0.03
A29: DCF Assumptions
A30: WACC | B30: 0.11
A31: Terminal growth | B31: 0.035
A32: Current diluted shares (m) | B32: 578.75099
A33: Current cash (m) | B33: 828.66
A34: Current debt (m) | B34: 152.395
A35: Current share price

Sheet Revenue Build
A1: Revenue Build by Driver
A3: $ in millions, except per-share data | B3: FY2023A | C3: FY2024A | D3: FY2025A | E3: FY2026E | F3: FY2027E | G3: FY2028E | H3: FY2029E | I3: FY2030E
A5: Launch Services
A6: Revenue | B6: 71.894 | C6: 125.376 | D6: 199.042 | E6: =D6*(1+Assumptions!E6) | F6: =E6*(1+Assumptions!F6) | G6: =F6*(1+Assumptions!G6) | H6: =G6*(1+Assumptions!H6) | I6: =H6*(1+Assumptions!I6)
A7: YoY Growth | C7: =C6/B6-1 | D7: =D6/C6-1 | E7: =E6/D6-1 | F7: =F6/E6-1 | G7: =G6/F6-1 | H7: =H6/G6-1 | I7: =I6/H6-1
A8: Gross Margin | B8: 0.112 | C8: 0.276 | D8: 0.408 | E8: =Assumptions!E9 | F8: =Assumptions!F9 | G8: =Assumptions!G9 | H8: =Assumptions!H9 | I8: =Assumptions!I9
A9: Gross Profit | B9: 8.067 | C9: 34.59 | D9: 81.27 | E9: =E6*E8 | F9: =F6*F8 | G9: =G6*G8 | H9: =H6*H8 | I9: =I6*I8
A11: Space Systems Products
A12: Revenue | B12: 156.56 | C12: 289.851 | D12: 371.617 | E12: =D12*(1+Assumptions!E7) | F12: =E12*(1+Assumptions!F7) | G12: =F12*(1+Assumptions!G7) | H12: =G12*(1+Assumptions!H7) | I12: =H12*(1+Assumptions!I7)
A13: YoY Growth | C13: =C12/B12-1 | D13: =D12/C12-1 | E13: =E12/D12-1 | F13: =F12/E12-1 | G13: =G12/F12-1 | H13: =H12/G12-1 | I13: =I12/H12-1
A14: Gross Margin | B14: 0.26327287 | C14: 0.26225888 | D14: 0.31960056 | E14: =Assumptions!E10 | F14: =Assumptions!F10 | G14: =Assumptions!G10 | H14: =Assumptions!H10 | I14: =Assumptions!I10
A15: Gross Profit | B15: 41.218 | C15: 76.016 | D15: 118.769 | E15: =E12*E14 | F15: =F12*F14 | G15: =G12*G14 | H15: =H12*H14 | I15: =I12*I14
A17: Space Systems Services
A18: Revenue | B18: 16.138 | C18: 20.987 | D18: 31.14 | E18: =D18*(1+Assumptions!E8) | F18: =E18*(1+Assumptions!F8) | G18: =F18*(1+Assumptions!G8) | H18: =G18*(1+Assumptions!H8) | I18: =H18*(1+Assumptions!I8)
A19: YoY Growth | C19: =C18/B18-1 | D19: =D18/C18-1 | E19: =E18/D18-1 | F19: =F18/E18-1 | G19: =G18/F18-1 | H19: =H18/G18-1 | I19: =I18/H18-1
A20: Gross Margin | B20: 0.13161482 | C20: 0.26411588 | D20: 0.22935132 | E20: =Assumptions!E11 | F20: =Assumptions!F11 | G20: =Assumptions!G11 | H20: =Assumptions!H11 | I20: =Assumptions!I11
A21: Gross Profit | B21: 2.124 | C21: 5.543 | D21: 7.142 | E21: =E18*E20 | F21: =F18*F20 | G21: =G18*G20 | H21: =H18*H20 | I21: =I18*I20
A23: Total Revenue and Gross Profit
A24: Space Systems Revenue | B24: =B12+B18 | C24: =C12+C18 | D24: =D12+D18 | E24: =E12+E18 | F24: =F12+F18 | G24: =G12+G18 | H24: =H12+H18 | I24: =I12+I18
A25: Total Revenue | B25: =B6+B24 | C25: =C6+C24 | D25: =D6+D24 | E25: =E6+E24 | F25: =F6+F24 | G25: =G6+G24 | H25: =H6+H24 | I25: =I6+I24
A26: Total Revenue Growth | B26: ="" | C26: =IFERROR(C25/B25-1,"") | D26: =IFERROR(D25/C25-1,"") | E26: =IFERROR(E25/D25-1,"") | F26: =IFERROR(F25/E25-1,"") | G26: =IFERROR(G25/F25-1,"") | H26: =IFERROR(H25/G25-1,"") | I26: =IFERROR(I25/H25-1,"")
A27: Total Gross Profit | B27: =B9+B15+B21 | C27: =C9+C15+C21 | D27: =D9+D15+D21 | E27: =E9+E15+E21 | F27: =F9+F15+F21 | G27: =G9+G15+G21 | H27: =H9+H15+H21 | I27: =I9+I15+I21
A28: Gross Margin | B28: =B27/B25 | C28: =C27/C25 | D28: =D27/D25 | E28: =E27/E25 | F28: =F27/F25 | G28: =G27/G25 | H28: =H27/H25 | I28: =I27/I25
A31: Backlog Memo
A32: Company backlog | D32: 1847.322
A33: % expected within 12 months | D33: 0.37

Sheet Income Statement
A1: Income Statement
A3: $ in millions, except per-share data | B3: FY2023A | C3: FY2024A | D3: FY2025A | E3: FY2026E | F3: FY2027E | G3: FY2028E | H3: FY2029E | I3: FY2030E
A4: Income Statement
A5: Revenue | B5: 244.592 | C5: 436.214 | D5: 601.799 | E5: ='Revenue Build'!E25 | F5: ='Revenue Build'!F25 | G5: ='Revenue Build'!G25 | H5: ='Revenue Build'!H25 | I5: ='Revenue Build'!I25
A6: Revenue Growth | B6: ="" | C6: =IFERROR(C5/B5-1,"") | D6: =IFERROR(D5/C5-1,"") | E6: =E5/D5-1 | F6: =F5/E5-1 | G6: =G5/F5-1 | H6: =H5/G5-1 | I6: =I5/H5-1
A8: Cost of Revenue | B8: 193.183 | C8: 320.065 | D8: 394.618 | E8: =E5-E9 | F8: =F5-F9 | G8: =G5-G9 | H8: =H5-H9 | I8: =I5-I9
A9: Gross Profit | B9: 51.409 | C9: 116.149 | D9: 207.181 | E9: ='Revenue Build'!E27 | F9: ='Revenue Build'!F27 | G9: ='Revenue Build'!G27 | H9: ='Revenue Build'!H27 | I9: ='Revenue Build'!I27
A10: Gross Margin | B10: =B9/B5 | C10: =C9/C5 | D10: =D9/D5 | E10: =E9/E5 | F10: =F9/F5 | G10: =G9/G5 | H10: =H9/H5 | I10: =I9/I5
A11: Operating Expenses
A12: R&D | B12: 119.054 | C12: 174.394 | D12: 270.716 | E12: =E5*Assumptions!E12 | F12: =F5*Assumptions!F12 | G12: =G5*Assumptions!G12 | H12: =H5*Assumptions!H12 | I12: =I5*Assumptions!I12
A13: SG&A | B13: 110.273 | C13: 131.556 | D13: 165.303 | E13: =E5*Assumptions!E13 | F13: =F5*Assumptions!F13 | G13: =G5*Assumptions!G13 | H13: =H5*Assumptions!H13 | I13: =I5*Assumptions!I13
A14: Operating Expenses | B14: 229.327 | C14: 305.95 | D14: 436.019 | E14: =E12+E13 | F14: =F12+F13 | G14: =G12+G13 | H14: =H12+H13 | I14: =I12+I13
A15: Operating Income | B15: -177.918 | C15: -189.801 | D15: -228.838 | E15: =E9-E14 | F15: =F9-F14 | G15: =G9-G14 | H15: =H9-H14 | I15: =I9-I14
A16: Operating Margin | B16: =B15/B5 | C16: =C15/C5 | D16: =D15/D5 | E16: =E15/E5 | F16: =F15/F5 | G16: =G15/G5 | H16: =H15/H5 | I16: =I15/I5
A18: D&A | B18: 29.744 | C18: 33.655 | D18: 43.935 | E18: =E5*Assumptions!E14 | F18: =F5*Assumptions!F14 | G18: =G5*Assumptions!G14 | H18: =H5*Assumptions!H14 | I18: =I5*Assumptions!I14
A19: EBITDA | B19: =B15+B18 | C19: =C15+C18 | D19: =D15+D18 | E19: =E15+E18 | F19: =F15+F18 | G19: =G15+G18 | H19: =H15+H18 | I19: =I15+I18
A20: EBITDA Margin | B20: =B19/B5 | C20: =C19/C5 | D20: =D19/D5 | E20: =E19/E5 | F20: =F19/F5 | G20: =G19/G5 | H20: =H19/H5 | I20: =I19/I5
A21: Below EBIT
A22: Interest Expense Memo | B22: 4.248 | C22: 3.954 | D22: 26.489 | E22: ='Balance Sheet'!E22*Assumptions!E24 | F22: ='Balance Sheet'!F22*Assumptions!F24 | G22: ='Balance Sheet'!G22*Assumptions!G24 | H22: ='Balance Sheet'!H22*Assumptions!H24 | I22: ='Balance Sheet'!I22*Assumptions!I24
A23: Net Nonoperating Income / Expense | B23: -1.003 | C23: 0.39 | D23: 2.941 | E23: =-E22 | F23: =-F22 | G23: =-G22 | H23: =-H22 | I23: =-I22
A24: Pre-tax Income | B24: =B15+B23 | C24: =C15+C23 | D24: =D15+D23 | E24: =E15+E23 | F24: =F15+F23 | G24: =G15+G23 | H24: =H15+H23 | I24: =I15+I23
A25: Tax Expense / (Benefit) | B25: 3.65 | C25: 0.764 | D25: -27.688 | E25: =IF(E24>0,E24*Assumptions!E23,0) | F25: =IF(F24>0,F24*Assumptions!F23,0) | G25: =IF(G24>0,G24*Assumptions!G23,0) | H25: =IF(H24>0,H24*Assumptions!H23,0) | I25: =IF(I24>0,I24*Assumptions!I23,0)
A26: Net Income | B26: -182.571 | C26: -190.175 | D26: -198.209 | E26: =E24-E25 | F26: =F24-F25 | G26: =G24-G25 | H26: =H24-H25 | I26: =I24-I25
A27: Net Margin | B27: =B26/B5 | C27: =C26/C5 | D27: =D26/D5 | E27: =E26/E5 | F27: =F26/F5 | G27: =G26/G5 | H27: =H26/H5 | I27: =I26/I5
A29: Diluted Shares | B29: 481.76806 | C29: 495.92986 | D29: 530.66478 | E29: =D29*(1+Assumptions!E25) | F29: =E29*(1+Assumptions!F25) | G29: =F29*(1+Assumptions!G25) | H29: =G29*(1+Assumptions!H25) | I29: =H29*(1+Assumptions!I25)
A30: EPS | B30: -3.8e-07 | C30: -3.8e-07 | D30: -3.7e-07 | E30: =E26/E29 | F30: =F26/F29 | G30: =G26/G29 | H30: =H26/H29 | I30: =I26/I29

Sheet Balance Sheet
A1: Balance Sheet
A3: $ in millions, except per-share data | B3: FY2023A | C3: FY2024A | D3: FY2025A | E3: FY2026E | F3: FY2027E | G3: FY2028E | H3: FY2029E | I3: FY2030E
A4: Assets
A5: Cash & Equivalents | B5: 162.518 | C5: 271.042 | D5: 828.66 | E5: ='Cash Flow'!E20 | F5: ='Cash Flow'!F20 | G5: ='Cash Flow'!G20 | H5: ='Cash Flow'!H20 | I5: ='Cash Flow'!I20
A6: Accounts Receivable | B6: 35.176 | C6: 36.44 | D6: 39.001 | E6: ='Income Statement'!E5*Assumptions!E17 | F6: ='Income Statement'!F5*Assumptions!F17 | G6: ='Income Statement'!G5*Assumptions!G17 | H6: ='Income Statement'!H5*Assumptions!H17 | I6: ='Income Statement'!I5*Assumptions!I17
A7: Inventory | B7: 107.857 | C7: 119.074 | D7: 158.407 | E7: ='Income Statement'!E5*Assumptions!E18 | F7: ='Income Statement'!F5*Assumptions!F18 | G7: ='Income Statement'!G5*Assumptions!G18 | H7: ='Income Statement'!H5*Assumptions!H18 | I7: ='Income Statement'!I5*Assumptions!I18
A8: Other Current Assets | B8: 66.949 | C8: 55.009 | D8: 89.953 | E8: ='Income Statement'!E5*Assumptions!E19 | F8: ='Income Statement'!F5*Assumptions!F19 | G8: ='Income Statement'!G5*Assumptions!G19 | H8: ='Income Statement'!H5*Assumptions!H19 | I8: ='Income Statement'!I5*Assumptions!I19
A9: Total Current Assets | B9: 476.722 | C9: 692.621 | D9: 1365.544 | E9: =SUM(E5:E8) | F9: =SUM(F5:F8) | G9: =SUM(G5:G8) | H9: =SUM(H5:H8) | I9: =SUM(I5:I8)
A11: PP&E, Net | B11: 145.409 | C11: 194.838 | D11: 319.473 | E11: =D11+'Cash Flow'!E11-'Income Statement'!E18 | F11: =E11+'Cash Flow'!F11-'Income Statement'!F18 | G11: =F11+'Cash Flow'!G11-'Income Statement'!G18 | H11: =G11+'Cash Flow'!H11-'Income Statement'!H18 | I11: =H11+'Cash Flow'!I11-'Income Statement'!I18
A12: Goodwill | B12: 71.02 | C12: 71.02 | D12: 205.75 | E12: =D12 | F12: =E12 | G12: =F12 | H12: =G12 | I12: =H12
A13: Intangibles | B13: 68.094 | C13: 58.637 | D13: 224.746 | E13: =D13 | F13: =E13 | G13: =F13 | H13: =G13 | I13: =H13
A14: Other Assets | B14: 18.914 | C14: 31.21 | D14: 15.672 | E14: =D14 | F14: =E14 | G14: =F14 | H14: =G14 | I14: =H14
A15: Total Assets | B15: 941.211 | C15: 1184.342 | D15: 2324.478 | E15: =SUM(E9,E11:E14) | F15: =SUM(F9,F11:F14) | G15: =SUM(G9,G11:G14) | H15: =SUM(H9,H11:H14) | I15: =SUM(I9,I11:I14)
A16: Liabilities and Equity
A17: Accounts Payable | B17: 29.303 | C17: 53.059 | D17: 72.699 | E17: ='Income Statement'!E5*Assumptions!E20 | F17: ='Income Statement'!F5*Assumptions!F20 | G17: ='Income Statement'!G5*Assumptions!G20 | H17: ='Income Statement'!H5*Assumptions!H20 | I17: ='Income Statement'!I5*Assumptions!I20
A18: Accrued Liabilities | B18: 5.59 | C18: 19.46 | D18: 19.299 | E18: ='Income Statement'!E5*Assumptions!E21 | F18: ='Income Statement'!F5*Assumptions!F21 | G18: ='Income Statement'!G5*Assumptions!G21 | H18: ='Income Statement'!H5*Assumptions!H21 | I18: ='Income Statement'!I5*Assumptions!I21
A19: Contract Liabilities | B19: 139.338 | C19: 216.16 | D19: 195.438 | E19: ='Income Statement'!E5*Assumptions!E22 | F19: ='Income Statement'!F5*Assumptions!F22 | G19: ='Income Statement'!G5*Assumptions!G22 | H19: ='Income Statement'!H5*Assumptions!H22 | I19: ='Income Statement'!I5*Assumptions!I22
A20: Current Liabilities | B20: 223.373 | C20: 339.525 | D20: 334.476 | E20: =SUM(E17:E19) | F20: =SUM(F17:F19) | G20: =SUM(G17:G19) | H20: =SUM(H17:H19) | I20: =SUM(I17:I19)
A22: Total Debt | B22: 110 | C22: 345.392 | D22: 152.395 | E22: =D22 | F22: =E22 | G22: =F22 | H22: =G22 | I22: =H22
A23: Lease / Other Noncurrent Liabilities | B23: 56.099 | C23: 51.965 | D23: 85.191 | E23: =D23 | F23: =E23 | G23: =F23 | H23: =G23 | I23: =H23
A24: Total Liabilities | B24: 386.667 | C24: 801.889 | D24: 602.624 | E24: =SUM(E20,E22:E23) | F24: =SUM(F20,F22:F23) | G24: =SUM(G20,G22:G23) | H24: =SUM(H20,H22:H23) | I24: =SUM(I20,I22:I23)
A26: Shareholders' Equity | B26: 554.544 | C26: 382.453 | D26: 1721.854 | E26: =E15-E24 | F26: =F15-F24 | G26: =G15-G24 | H26: =H15-H24 | I26: =I15-I24
A27: Liabilities + Equity | B27: 941.211 | C27: 1184.342 | D27: 2324.478 | E27: =E24+E26 | F27: =F24+F26 | G27: =G24+G26 | H27: =H24+H26 | I27: =I24+I26
A28: Checks / Memo
A29: Balance Check | B29: =B15-B27 | C29: =C15-C27 | D29: =D15-D27 | E29: =E15-E27 | F29: =F15-F27 | G29: =G15-G27 | H29: =H15-H27 | I29: =I15-I27
A31: Net Cash / (Debt) | B31: =B5-B22 | C31: =C5-C22 | D31: =D5-D22 | E31: =E5-E22 | F31: =F5-F22 | G31: =G5-G22 | H31: =H5-H22 | I31: =I5-I22

Sheet Cash Flow
A1: Cash Flow Statement
A3: $ in millions, except per-share data | B3: FY2023A | C3: FY2024A | D3: FY2025A | E3: FY2026E | F3: FY2027E | G3: FY2028E | H3: FY2029E | I3: FY2030E
A4: Operating Cash Flow
A5: Net Income | B5: -182.571 | C5: -190.175 | D5: -198.209 | E5: ='Income Statement'!E26 | F5: ='Income Statement'!F26 | G5: ='Income Statement'!G26 | H5: ='Income Statement'!H26 | I5: ='Income Statement'!I26
A6: D&A | B6: 29.744 | C6: 33.655 | D6: 43.935 | E6: ='Income Statement'!E18 | F6: ='Income Statement'!F18 | G6: ='Income Statement'!G18 | H6: ='Income Statement'!H18 | I6: ='Income Statement'!I18
A7: Stock-Based Compensation | B7: 53.461 | C7: 56.816 | D7: 71.099 | E7: ='Income Statement'!E5*Assumptions!E15 | F7: ='Income Statement'!F5*Assumptions!F15 | G7: ='Income Statement'!G5*Assumptions!G15 | H7: ='Income Statement'!H5*Assumptions!H15 | I7: ='Income Statement'!I5*Assumptions!I15
A8: Change in NWC | B8: =B5+B6+B7-B9 | C8: =C5+C6+C7-C9 | D8: =D5+D6+D7-D9 | E8: =('Balance Sheet'!E6+'Balance Sheet'!E7+'Balance Sheet'!E8-'Balance Sheet'!E17-'Balance Sheet'!E18-'Balance Sheet'!E19)-('Balance Sheet'!D6+'Balance Sheet'!D7+'Balance Sheet'!D8-'Balance Sheet'!D17-'Balance Sheet'!D18-'Balance Sheet'!D19) | F8: =('Balance Sheet'!F6+'Balance Sheet'!F7+'Balance Sheet'!F8-'Balance Sheet'!F17-'Balance Sheet'!F18-'Balance Sheet'!F19)-('Balance Sheet'!E6+'Balance Sheet'!E7+'Balance Sheet'!E8-'Balance Sheet'!E17-'Balance Sheet'!E18-'Balance Sheet'!E19) | G8: =('Balance Sheet'!G6+'Balance Sheet'!G7+'Balance Sheet'!G8-'Balance Sheet'!G17-'Balance Sheet'!G18-'Balance Sheet'!G19)-('Balance Sheet'!F6+'Balance Sheet'!F7+'Balance Sheet'!F8-'Balance Sheet'!F17-'Balance Sheet'!F18-'Balance Sheet'!F19) | H8: =('Balance Sheet'!H6+'Balance Sheet'!H7+'Balance Sheet'!H8-'Balance Sheet'!H17-'Balance Sheet'!H18-'Balance Sheet'!H19)-('Balance Sheet'!G6+'Balance Sheet'!G7+'Balance Sheet'!G8-'Balance Sheet'!G17-'Balance Sheet'!G18-'Balance Sheet'!G19) | I8: =('Balance Sheet'!I6+'Balance Sheet'!I7+'Balance Sheet'!I8-'Balance Sheet'!I17-'Balance Sheet'!I18-'Balance Sheet'!I19)-('Balance Sheet'!H6+'Balance Sheet'!H7+'Balance Sheet'!H8-'Balance Sheet'!H17-'Balance Sheet'!H18-'Balance Sheet'!H19)
A9: Cash Flow from Operations | B9: -98.867 | C9: -48.89 | D9: -165.521 | E9: =E5+E6+E7-E8 | F9: =F5+F6+F7-F8 | G9: =G5+G6+G7-G8 | H9: =H5+H6+H7-H8 | I9: =I5+I6+I7-I8
A10: Investing Cash Flow
A11: CapEx | B11: 54.707 | C11: 67.093 | D11: 156.285 | E11: ='Income Statement'!E5*Assumptions!E16 | F11: ='Income Statement'!F5*Assumptions!F16 | G11: ='Income Statement'!G5*Assumptions!G16 | H11: ='Income Statement'!H5*Assumptions!H16 | I11: ='Income Statement'!I5*Assumptions!I16
A12: Acquisitions | B12: 18.966 | C12: 0 | D12: 132.441 | E12: =0 | F12: =0 | G12: =0 | H12: =0 | I12: =0
A13: Cash Flow from Investing | B13: 12.018 | C13: -98.327 | D13: -347.397 | E13: =-E11-E12 | F13: =-F11-F12 | G13: =-G11-G12 | H13: =-H11-H12 | I13: =-I11-I12
A14: Financing Cash Flow
A15: Debt / Equity Financing | B15: =B16 | C15: =C16 | D15: =D16 | E15: =0 | F15: =0 | G15: =0 | H15: =0 | I15: =0
A16: Cash Flow from Financing | B16: 7.369 | C16: 256.682 | D16: 1071.271 | E16: =E15 | F16: =F15 | G16: =G15 | H16: =H15 | I16: =I15
A17: Cash Tie-Out
A18: Beginning Cash | B18: =B20-B19 | C18: =B20 | D18: =C20 | E18: =D20 | F18: =E20 | G18: =F20 | H18: =G20 | I18: =H20
A19: Net Change in Cash | B19: -79.437 | C19: 108.868 | D19: 558.243 | E19: =E9+E13+E16 | F19: =F9+F13+F16 | G19: =G9+G13+G16 | H19: =H9+H13+H16 | I19: =I9+I13+I16
A20: Ending Cash | B20: 166.434 | C20: 275.302 | D20: 833.545 | E20: =E18+E19 | F20: =F18+F19 | G20: =G18+G19 | H20: =H18+H19 | I20: =I18+I19
A21: Cash Tie Check | B21: =B20-'Balance Sheet'!B5 | C21: =C20-'Balance Sheet'!C5 | D21: =D20-'Balance Sheet'!D5 | E21: =E20-'Balance Sheet'!E5 | F21: =F20-'Balance Sheet'!F5 | G21: =G20-'Balance Sheet'!G5 | H21: =H20-'Balance Sheet'!H5 | I21: =I20-'Balance Sheet'!I5
A23: Unlevered FCF | B23: ='Income Statement'!B15*(1-21%)+B6-B11-B8 | C23: ='Income Statement'!C15*(1-21%)+C6-C11-C8 | D23: ='Income Statement'!D15*(1-21%)+D6-D11-D8 | E23: ='Income Statement'!E15*(1-Assumptions!E23)+E6-E11-E8 | F23: ='Income Statement'!F15*(1-Assumptions!F23)+F6-F11-F8 | G23: ='Income Statement'!G15*(1-Assumptions!G23)+G6-G11-G8 | H23: ='Income Statement'!H15*(1-Assumptions!H23)+H6-H11-H8 | I23: ='Income Statement'!I15*(1-Assumptions!I23)+I6-I11-I8

Sheet DCF
A1: DCF Valuation
B3: FY2026E | C3: FY2027E | D3: FY2028E | E3: FY2029E | F3: FY2030E
A4: Unlevered Free Cash Flow
A5: Revenue | B5: ='Income Statement'!E5 | C5: ='Income Statement'!F5 | D5: ='Income Statement'!G5 | E5: ='Income Statement'!H5 | F5: ='Income Statement'!I5
A6: EBIT | B6: ='Income Statement'!E15 | C6: ='Income Statement'!F15 | D6: ='Income Statement'!G15 | E6: ='Income Statement'!H15 | F6: ='Income Statement'!I15
A7: Tax Rate | B7: =Assumptions!E23 | C7: =Assumptions!F23 | D7: =Assumptions!G23 | E7: =Assumptions!H23 | F7: =Assumptions!I23
A8: NOPAT | B8: =B6*(1-B7) | C8: =C6*(1-C7) | D8: =D6*(1-D7) | E8: =E6*(1-E7) | F8: =F6*(1-F7)
A9: D&A | B9: ='Income Statement'!E18 | C9: ='Income Statement'!F18 | D9: ='Income Statement'!G18 | E9: ='Income Statement'!H18 | F9: ='Income Statement'!I18
A10: CapEx | B10: ='Cash Flow'!E11 | C10: ='Cash Flow'!F11 | D10: ='Cash Flow'!G11 | E10: ='Cash Flow'!H11 | F10: ='Cash Flow'!I11
A11: Change in NWC | B11: ='Cash Flow'!E8 | C11: ='Cash Flow'!F8 | D11: ='Cash Flow'!G8 | E11: ='Cash Flow'!H8 | F11: ='Cash Flow'!I8
A12: Unlevered FCF | B12: =B8+B9-B10-B11 | C12: =C8+C9-C10-C11 | D12: =D8+D9-D10-D11 | E12: =E8+E9-E10-E11 | F12: =F8+F9-F10-F11
A14: Discount Factor | B14: =1/(1+Assumptions!B30)^1 | C14: =1/(1+Assumptions!B30)^2 | D14: =1/(1+Assumptions!B30)^3 | E14: =1/(1+Assumptions!B30)^4 | F14: =1/(1+Assumptions!B30)^5
A15: PV of FCF | B15: =B12*B14 | C15: =C12*C14 | D15: =D12*D14 | E15: =E12*E14 | F15: =F12*F14
A17: Terminal Growth | B17: =Assumptions!B31 | C17: =Assumptions!B31 | D17: =Assumptions!B31 | E17: =Assumptions!B31 | F17: =Assumptions!B31
A18: Terminal Value | F18: =F12*(1+Assumptions!B31)/(Assumptions!B30-Assumptions!B31)
A19: PV of Terminal Value | F19: =F18*F14
A21: Valuation Summary
A22: PV of FCF | B22: =SUM(B15:F15)
A23: PV of Terminal Value | B23: =F19
A24: Enterprise Value | B24: =B22+B23
A25: Cash | B25: =Assumptions!B33
A26: Debt | B26: =Assumptions!B34
A27: Equity Value | B27: =B24+B25-B26
A28: Diluted Shares | B28: =Assumptions!B32
A29: Implied Value / Share | B29: =B27/B28
A30: Current Share Price | B30: =Assumptions!B35
A31: Upside / (Downside) | B31: =IF(B30>0,B29/B30-1,"")

Sheet Sensitivity
A1: DCF Sensitivity: WACC vs Terminal Growth
A3: Implied Value / Share
A4: WACC \ Terminal g | B4: =Assumptions!B31-0.010 | C4: =Assumptions!B31-0.005 | D4: =Assumptions!B31+0.000 | E4: =Assumptions!B31+0.005 | F4: =Assumptions!B31+0.010
A5: =Assumptions!B30-0.020 | B5: =(DCF!B12/(1+$A5)^1+DCF!C12/(1+$A5)^2+DCF!D12/(1+$A5)^3+DCF!E12/(1+$A5)^4+DCF!F12/(1+$A5)^5+DCF!F12*(1+B$4)/($A5-B$4)/(1+$A5)^5+DCF!B25-DCF!B26)/DCF!B28 | C5: =(DCF!B12/(1+$A5)^1+DCF!C12/(1+$A5)^2+DCF!D12/(1+$A5)^3+DCF!E12/(1+$A5)^4+DCF!F12/(1+$A5)^5+DCF!F12*(1+C$4)/($A5-C$4)/(1+$A5)^5+DCF!B25-DCF!B26)/DCF!B28 | D5: =(DCF!B12/(1+$A5)^1+DCF!C12/(1+$A5)^2+DCF!D12/(1+$A5)^3+DCF!E12/(1+$A5)^4+DCF!F12/(1+$A5)^5+DCF!F12*(1+D$4)/($A5-D$4)/(1+$A5)^5+DCF!B25-DCF!B26)/DCF!B28 | E5: =(DCF!B12/(1+$A5)^1+DCF!C12/(1+$A5)^2+DCF!D12/(1+$A5)^3+DCF!E12/(1+$A5)^4+DCF!F12/(1+$A5)^5+DCF!F12*(1+E$4)/($A5-E$4)/(1+$A5)^5+DCF!B25-DCF!B26)/DCF!B28 | F5: =(DCF!B12/(1+$A5)^1+DCF!C12/(1+$A5)^2+DCF!D12/(1+$A5)^3+DCF!E12/(1+$A5)^4+DCF!F12/(1+$A5)^5+DCF!F12*(1+F$4)/($A5-F$4)/(1+$A5)^5+DCF!B25-DCF!B26)/DCF!B28
A6: =Assumptions!B30-0.010 | B6: =(DCF!B12/(1+$A6)^1+DCF!C12/(1+$A6)^2+DCF!D12/(1+$A6)^3+DCF!E12/(1+$A6)^4+DCF!F12/(1+$A6)^5+DCF!F12*(1+B$4)/($A6-B$4)/(1+$A6)^5+DCF!B25-DCF!B26)/DCF!B28 | C6: =(DCF!B12/(1+$A6)^1+DCF!C12/(1+$A6)^2+DCF!D12/(1+$A6)^3+DCF!E12/(1+$A6)^4+DCF!F12/(1+$A6)^5+DCF!F12*(1+C$4)/($A6-C$4)/(1+$A6)^5+DCF!B25-DCF!B26)/DCF!B28 | D6: =(DCF!B12/(1+$A6)^1+DCF!C12/(1+$A6)^2+DCF!D12/(1+$A6)^3+DCF!E12/(1+$A6)^4+DCF!F12/(1+$A6)^5+DCF!F12*(1+D$4)/($A6-D$4)/(1+$A6)^5+DCF!B25-DCF!B26)/DCF!B28 | E6: =(DCF!B12/(1+$A6)^1+DCF!C12/(1+$A6)^2+DCF!D12/(1+$A6)^3+DCF!E12/(1+$A6)^4+DCF!F12/(1+$A6)^5+DCF!F12*(1+E$4)/($A6-E$4)/(1+$A6)^5+DCF!B25-DCF!B26)/DCF!B28 | F6: =(DCF!B12/(1+$A6)^1+DCF!C12/(1+$A6)^2+DCF!D12/(1+$A6)^3+DCF!E12/(1+$A6)^4+DCF!F12/(1+$A6)^5+DCF!F12*(1+F$4)/($A6-F$4)/(1+$A6)^5+DCF!B25-DCF!B26)/DCF!B28
A7: =Assumptions!B30+0.000 | B7: =(DCF!B12/(1+$A7)^1+DCF!C12/(1+$A7)^2+DCF!D12/(1+$A7)^3+DCF!E12/(1+$A7)^4+DCF!F12/(1+$A7)^5+DCF!F12*(1+B$4)/($A7-B$4)/(1+$A7)^5+DCF!B25-DCF!B26)/DCF!B28 | C7: =(DCF!B12/(1+$A7)^1+DCF!C12/(1+$A7)^2+DCF!D12/(1+$A7)^3+DCF!E12/(1+$A7)^4+DCF!F12/(1+$A7)^5+DCF!F12*(1+C$4)/($A7-C$4)/(1+$A7)^5+DCF!B25-DCF!B26)/DCF!B28 | D7: =(DCF!B12/(1+$A7)^1+DCF!C12/(1+$A7)^2+DCF!D12/(1+$A7)^3+DCF!E12/(1+$A7)^4+DCF!F12/(1+$A7)^5+DCF!F12*(1+D$4)/($A7-D$4)/(1+$A7)^5+DCF!B25-DCF!B26)/DCF!B28 | E7: =(DCF!B12/(1+$A7)^1+DCF!C12/(1+$A7)^2+DCF!D12/(1+$A7)^3+DCF!E12/(1+$A7)^4+DCF!F12/(1+$A7)^5+DCF!F12*(1+E$4)/($A7-E$4)/(1+$A7)^5+DCF!B25-DCF!B26)/DCF!B28 | F7: =(DCF!B12/(1+$A7)^1+DCF!C12/(1+$A7)^2+DCF!D12/(1+$A7)^3+DCF!E12/(1+$A7)^4+DCF!F12/(1+$A7)^5+DCF!F12*(1+F$4)/($A7-F$4)/(1+$A7)^5+DCF!B25-DCF!B26)/DCF!B28
A8: =Assumptions!B30+0.010 | B8: =(DCF!B12/(1+$A8)^1+DCF!C12/(1+$A8)^2+DCF!D12/(1+$A8)^3+DCF!E12/(1+$A8)^4+DCF!F12/(1+$A8)^5+DCF!F12*(1+B$4)/($A8-B$4)/(1+$A8)^5+DCF!B25-DCF!B26)/DCF!B28 | C8: =(DCF!B12/(1+$A8)^1+DCF!C12/(1+$A8)^2+DCF!D12/(1+$A8)^3+DCF!E12/(1+$A8)^4+DCF!F12/(1+$A8)^5+DCF!F12*(1+C$4)/($A8-C$4)/(1+$A8)^5+DCF!B25-DCF!B26)/DCF!B28 | D8: =(DCF!B12/(1+$A8)^1+DCF!C12/(1+$A8)^2+DCF!D12/(1+$A8)^3+DCF!E12/(1+$A8)^4+DCF!F12/(1+$A8)^5+DCF!F12*(1+D$4)/($A8-D$4)/(1+$A8)^5+DCF!B25-DCF!B26)/DCF!B28 | E8: =(DCF!B12/(1+$A8)^1+DCF!C12/(1+$A8)^2+DCF!D12/(1+$A8)^3+DCF!E12/(1+$A8)^4+DCF!F12/(1+$A8)^5+DCF!F12*(1+E$4)/($A8-E$4)/(1+$A8)^5+DCF!B25-DCF!B26)/DCF!B28 | F8: =(DCF!B12/(1+$A8)^1+DCF!C12/(1+$A8)^2+DCF!D12/(1+$A8)^3+DCF!E12/(1+$A8)^4+DCF!F12/(1+$A8)^5+DCF!F12*(1+F$4)/($A8-F$4)/(1+$A8)^5+DCF!B25-DCF!B26)/DCF!B28
A9: =Assumptions!B30+0.020 | B9: =(DCF!B12/(1+$A9)^1+DCF!C12/(1+$A9)^2+DCF!D12/(1+$A9)^3+DCF!E12/(1+$A9)^4+DCF!F12/(1+$A9)^5+DCF!F12*(1+B$4)/($A9-B$4)/(1+$A9)^5+DCF!B25-DCF!B26)/DCF!B28 | C9: =(DCF!B12/(1+$A9)^1+DCF!C12/(1+$A9)^2+DCF!D12/(1+$A9)^3+DCF!E12/(1+$A9)^4+DCF!F12/(1+$A9)^5+DCF!F12*(1+C$4)/($A9-C$4)/(1+$A9)^5+DCF!B25-DCF!B26)/DCF!B28 | D9: =(DCF!B12/(1+$A9)^1+DCF!C12/(1+$A9)^2+DCF!D12/(1+$A9)^3+DCF!E12/(1+$A9)^4+DCF!F12/(1+$A9)^5+DCF!F12*(1+D$4)/($A9-D$4)/(1+$A9)^5+DCF!B25-DCF!B26)/DCF!B28 | E9: =(DCF!B12/(1+$A9)^1+DCF!C12/(1+$A9)^2+DCF!D12/(1+$A9)^3+DCF!E12/(1+$A9)^4+DCF!F12/(1+$A9)^5+DCF!F12*(1+E$4)/($A9-E$4)/(1+$A9)^5+DCF!B25-DCF!B26)/DCF!B28 | F9: =(DCF!B12/(1+$A9)^1+DCF!C12/(1+$A9)^2+DCF!D12/(1+$A9)^3+DCF!E12/(1+$A9)^4+DCF!F12/(1+$A9)^5+DCF!F12*(1+F$4)/($A9-F$4)/(1+$A9)^5+DCF!B25-DCF!B26)/DCF!B28

Sheet Checks
A1: Model Checks
A3: Check | B3: Formula Result | C3: Status
A4: Revenue build equals IS revenue FY2025 | B4: ='Revenue Build'!D25-'Income Statement'!D5 | C4: =IF(ABS(B4)<0.01,"OK","Review")
A5: Revenue build equals IS revenue FY2030E | B5: ='Revenue Build'!I25-'Income Statement'!I5 | C5: =IF(ABS(B5)<0.01,"OK","Review")
A6: BS balances FY2025 | B6: ='Balance Sheet'!D29 | C6: =IF(ABS(B6)<0.01,"OK","Review")
A7: BS balances FY2030E | B7: ='Balance Sheet'!I29 | C7: =IF(ABS(B7)<0.01,"OK","Review")
A8: Cash ties FY2030E | B8: ='Cash Flow'!I21 | C8: =IF(ABS(B8)<0.01,"OK","Review")
A9: DCF uses FY2030E UFCF | B9: ='DCF'!F12-'Cash Flow'!I23 | C9: =IF(ABS(B9)<0.01,"OK","Review")
